meteocalc/__init__.py
meteocalc/classutils.py
meteocalc/dewpoint.py
meteocalc/feelslike_temperature.py
meteocalc/heatindex.py
meteocalc/temperature.py
meteocalc/windchill.py
meteocalc-1.1.0.dist-info/LICENSE
meteocalc-1.1.0.dist-info/METADATA
meteocalc-1.1.0.dist-info/WHEEL
meteocalc-1.1.0.dist-info/top_level.txt
meteocalc-1.1.0.dist-info/RECORD
