Metadata-Version: 2.1
Name: meteocalc
Version: 1.1.0
Summary: Functions for calculation of meteorological variables.
Home-page: https://github.com/malexer/meteocalc
Author: Alex (Oleksii) Markov
Author-email: alex@markovs.me
License: MIT
Keywords: meteorology meteo dew heat heatindex humiture humidex feels like temp temperature wind chill
Platform: UNKNOWN
Classifier: Development Status :: 4 - Beta
Classifier: Intended Audience :: Developers
Classifier: Intended Audience :: Science/Research
Classifier: Topic :: Software Development :: Libraries :: Python Modules
Classifier: Topic :: Scientific/Engineering :: Atmospheric Science
Classifier: License :: OSI Approved :: MIT License
Classifier: Programming Language :: Python :: 2
Classifier: Programming Language :: Python :: 2.7
Classifier: Programming Language :: Python :: 3
Classifier: Programming Language :: Python :: 3.2
Classifier: Programming Language :: Python :: 3.3
Classifier: Programming Language :: Python :: 3.4
Classifier: Programming Language :: Python :: 3.5
Classifier: Programming Language :: Python :: 3.6
Classifier: Programming Language :: Python :: 3.7
